{
  "producto": "Rayos SIGIF/GVA KMZ 24h convertido a GeoJSON",
  "fuente": "https://prevencionincendiosgva.es/Meteorologia/GetRayos24hKML",
  "actualizado_utc": "2026-07-24T07:42:20+00:00",
  "bbox_valencia": {
    "lon_min": -1.7,
    "lat_min": 38.6,
    "lon_max": 0.05,
    "lat_max": 40.25
  },
  "rayos_descargados_en_bbox": 6,
  "rayos_nuevos": 4,
  "rayos_repetidos": 2,
  "rayos_24h": 6,
  "rayos_48h": 6,
  "rayos_72h": 271,
  "archivos": [
    "rayos_24h.geojson",
    "rayos_48h.geojson",
    "rayos_72h.geojson",
    "rayos_historico.geojson"
  ],
  "nota": "SIGIF/GVA proporciona un KMZ con rayos de las últimas 24 h. Este script acumula histórico propio hasta 72 h. Si el KML no trae hora individual de cada rayo, se usa la primera hora de captura."
}